benchmarks/__init__.py
benchmarks/helpers.py
featherstore/__init__.py
featherstore/_metadata.py
featherstore/_utils.py
featherstore/connection.py
featherstore/snapshot.py
featherstore/store.py
featherstore/table.py
featherstore/_table/__init__.py
featherstore/_table/_indexers.py
featherstore/_table/_raise_if.py
featherstore/_table/_table_utils.py
featherstore/_table/add_cols.py
featherstore/_table/append.py
featherstore/_table/astype.py
featherstore/_table/common.py
featherstore/_table/drop.py
featherstore/_table/insert.py
featherstore/_table/misc.py
featherstore/_table/read.py
featherstore/_table/rename_cols.py
featherstore/_table/update.py
featherstore/_table/write.py
FeatherStore-0.2.0.dist-info/LICENSE
FeatherStore-0.2.0.dist-info/METADATA
FeatherStore-0.2.0.dist-info/WHEEL
FeatherStore-0.2.0.dist-info/top_level.txt
FeatherStore-0.2.0.dist-info/RECORD
