Metadata-Version: 2.1
Name: FeatherStore
Version: 0.2.0
Summary: High performance datastore built upon Apache Arrow & Feather
Home-page: https://github.com/Hakonmh/featherstore
Author: Håkon Magne Holmen
Author-email: haakonholmen@hotmail.com
License: MIT
Project-URL: Documentation, https://featherstore.readthedocs.io/en/stable/
Keywords: feather arrow pandas polars datastore
Classifier: Development Status :: 3 - Alpha
Classifier: Topic :: Database
Classifier: Topic :: Database :: Database Engines/Servers
Classifier: License :: OSI Approved :: MIT License
Classifier: Programming Language :: Python :: 3.8
Classifier: Programming Language :: Python :: 3.9
Classifier: Programming Language :: Python :: 3.10
Requires-Python: >=3.8
License-File: LICENSE
Requires-Dist: pandas (>=1.1.0)
Requires-Dist: polars[timezone] (>=0.14.11)
Requires-Dist: pyarrow (>=7.0.0)
